{
  "fetchedAt": "2026-07-16T04:14:14.960Z",
  "rankings": [
    {
      "rank": 1,
      "bladeCode": "BX-34",
      "bladeZh": "苍穹龙骑士(左)",
      "ratchet": "5-60",
      "bit": "E",
      "score": 1468,
      "wins": 791,
      "first": 152,
      "second": 78,
      "third": 561,
      "champRate": 0.1922,
      "recent90": 1,
      "lastDate": "2026-12-02"
    },
    {
      "rank": 2,
      "bladeCode": "UX-03",
      "bladeZh": "魔导神杖",
      "ratchet": "1-60",
      "bit": "H",
      "score": 1433,
      "wins": 652,
      "first": 169,
      "second": 96,
      "third": 387,
      "champRate": 0.2592,
      "recent90": 3,
      "lastDate": "2026-12-02"
    },
    {
      "rank": 3,
      "bladeCode": "UX-03",
      "bladeZh": "魔导神杖",
      "ratchet": "9-60",
      "bit": "B",
      "score": 1159,
      "wins": 644,
      "first": 117,
      "second": 61,
      "third": 466,
      "champRate": 0.1817,
      "recent90": 0,
      "lastDate": "2026-09-01"
    },
    {
      "rank": 4,
      "bladeCode": "BX-23",
      "bladeZh": "凤凰飞翼",
      "ratchet": "1-60",
      "bit": "R",
      "score": 662,
      "wins": 331,
      "first": 78,
      "second": 24,
      "third": 229,
      "champRate": 0.2356,
      "recent90": 1,
      "lastDate": "2026-12-02"
    },
    {
      "rank": 5,
      "bladeCode": "BX-34",
      "bladeZh": "苍穹龙骑士(左)",
      "ratchet": "9-60",
      "bit": "E",
      "score": 523,
      "wins": 268,
      "first": 56,
      "second": 26,
      "third": 186,
      "champRate": 0.209,
      "recent90": 3,
      "lastDate": "2026-12-02"
    },
    {
      "rank": 6,
      "bladeCode": "BX-23",
      "bladeZh": "凤凰飞翼",
      "ratchet": "3-60",
      "bit": "R",
      "score": 523,
      "wins": 283,
      "first": 53,
      "second": 24,
      "third": 206,
      "champRate": 0.1873,
      "recent90": 0,
      "lastDate": "2026-09-01"
    },
    {
      "rank": 7,
      "bladeCode": "BX-24-01",
      "bladeZh": "飞龙旋翼(绿)",
      "ratchet": "9-60",
      "bit": "K",
      "score": 427,
      "wins": 177,
      "first": 53,
      "second": 26,
      "third": 98,
      "champRate": 0.2994,
      "recent90": 2,
      "lastDate": "2026-12-02"
    },
    {
      "rank": 8,
      "bladeCode": "UX-03",
      "bladeZh": "魔导神杖",
      "ratchet": "3-60",
      "bit": "B",
      "score": 408,
      "wins": 194,
      "first": 50,
      "second": 17,
      "third": 127,
      "champRate": 0.2577,
      "recent90": 0,
      "lastDate": "2026-09-01"
    },
    {
      "rank": 9,
      "bladeCode": "UX-15-01",
      "bladeZh": "鲛鲨狂鳞",
      "ratchet": "3-60",
      "bit": "LR",
      "score": 320,
      "wins": 143,
      "first": 37,
      "second": 17,
      "third": 89,
      "champRate": 0.2587,
      "recent90": 1,
      "lastDate": "2026-11-01"
    },
    {
      "rank": 10,
      "bladeCode": "UX-15-01",
      "bladeZh": "鲛鲨狂鳞",
      "ratchet": "1-70",
      "bit": "LR",
      "score": 312,
      "wins": 130,
      "first": 38,
      "second": 17,
      "third": 75,
      "champRate": 0.2923,
      "recent90": 1,
      "lastDate": "2026-12-02"
    },
    {
      "rank": 11,
      "bladeCode": "BX-23",
      "bladeZh": "凤凰飞翼",
      "ratchet": "1-60",
      "bit": "LR",
      "score": 286,
      "wins": 149,
      "first": 28,
      "second": 20,
      "third": 101,
      "champRate": 0.1879,
      "recent90": 0,
      "lastDate": "2026-09-01"
    },
    {
      "rank": 12,
      "bladeCode": "BX-23",
      "bladeZh": "凤凰飞翼",
      "ratchet": "3-60",
      "bit": "LR",
      "score": 276,
      "wins": 145,
      "first": 28,
      "second": 14,
      "third": 103,
      "champRate": 0.1931,
      "recent90": 0,
      "lastDate": "2026-09-01"
    },
    {
      "rank": 13,
      "bladeCode": "BX-34",
      "bladeZh": "苍穹龙骑士(左)",
      "ratchet": "1-60",
      "bit": "E",
      "score": 256,
      "wins": 136,
      "first": 26,
      "second": 14,
      "third": 96,
      "champRate": 0.1912,
      "recent90": 0,
      "lastDate": "2026-04-25"
    },
    {
      "rank": 14,
      "bladeCode": "BX-31-02",
      "bladeZh": "暴龙霸击",
      "ratchet": "1-60",
      "bit": "R",
      "score": 239,
      "wins": 120,
      "first": 24,
      "second": 20,
      "third": 76,
      "champRate": 0.2,
      "recent90": 0,
      "lastDate": "2025-11-02"
    },
    {
      "rank": 15,
      "bladeCode": "UX-03",
      "bladeZh": "魔导神杖",
      "ratchet": "9-60",
      "bit": "FB",
      "score": 236,
      "wins": 118,
      "first": 23,
      "second": 18,
      "third": 77,
      "champRate": 0.1949,
      "recent90": 1,
      "lastDate": "2026-12-02"
    },
    {
      "rank": 16,
      "bladeCode": "UX-15-01",
      "bladeZh": "鲛鲨狂鳞",
      "ratchet": "4-50",
      "bit": "LR",
      "score": 212,
      "wins": 96,
      "first": 25,
      "second": 8,
      "third": 63,
      "champRate": 0.2604,
      "recent90": 0,
      "lastDate": "2026-09-01"
    },
    {
      "rank": 17,
      "bladeCode": "UX-03",
      "bladeZh": "魔导神杖",
      "ratchet": "1-70",
      "bit": "H",
      "score": 210,
      "wins": 81,
      "first": 28,
      "second": 6,
      "third": 47,
      "champRate": 0.3457,
      "recent90": 2,
      "lastDate": "2026-12-02"
    },
    {
      "rank": 18,
      "bladeCode": "UX-03",
      "bladeZh": "魔导神杖",
      "ratchet": "9-60",
      "bit": "H",
      "score": 209,
      "wins": 97,
      "first": 24,
      "second": 13,
      "third": 60,
      "champRate": 0.2474,
      "recent90": 0,
      "lastDate": "2026-04-26"
    },
    {
      "rank": 19,
      "bladeCode": "BXH-10",
      "bladeZh": "空力天马",
      "ratchet": "1-60",
      "bit": "R",
      "score": 201,
      "wins": 110,
      "first": 17,
      "second": 14,
      "third": 79,
      "champRate": 0.1545,
      "recent90": 0,
      "lastDate": "2026-04-26"
    },
    {
      "rank": 20,
      "bladeCode": "UX-08",
      "bladeZh": "霜辉银狼",
      "ratchet": "9-60",
      "bit": "FB",
      "score": 193,
      "wins": 110,
      "first": 15,
      "second": 13,
      "third": 82,
      "champRate": 0.1364,
      "recent90": 0,
      "lastDate": "2026-09-01"
    },
    {
      "rank": 21,
      "bladeCode": "BX-23",
      "bladeZh": "凤凰飞翼",
      "ratchet": "3-60",
      "bit": "P",
      "score": 183,
      "wins": 105,
      "first": 14,
      "second": 15,
      "third": 76,
      "champRate": 0.1333,
      "recent90": 0,
      "lastDate": "2025-12-28"
    },
    {
      "rank": 22,
      "bladeCode": "UX-08",
      "bladeZh": "霜辉银狼",
      "ratchet": "9-60",
      "bit": "H",
      "score": 173,
      "wins": 81,
      "first": 20,
      "second": 8,
      "third": 53,
      "champRate": 0.2469,
      "recent90": 0,
      "lastDate": "2026-02-20"
    },
    {
      "rank": 23,
      "bladeCode": "UX-15-01",
      "bladeZh": "鲛鲨狂鳞",
      "ratchet": "1-60",
      "bit": "LR",
      "score": 172,
      "wins": 72,
      "first": 21,
      "second": 9,
      "third": 42,
      "champRate": 0.2917,
      "recent90": 0,
      "lastDate": "2026-09-01"
    },
    {
      "rank": 24,
      "bladeCode": "UX-03",
      "bladeZh": "魔导神杖",
      "ratchet": "9-60",
      "bit": "LO",
      "score": 155,
      "wins": 69,
      "first": 20,
      "second": 2,
      "third": 47,
      "champRate": 0.2899,
      "recent90": 0,
      "lastDate": "2026-03-28"
    },
    {
      "rank": 25,
      "bladeCode": "UX-14",
      "bladeZh": "天蝎长矛",
      "ratchet": "9-60",
      "bit": "FB",
      "score": 153,
      "wins": 56,
      "first": 21,
      "second": 9,
      "third": 26,
      "champRate": 0.375,
      "recent90": 0,
      "lastDate": "2026-09-01"
    },
    {
      "rank": 26,
      "bladeCode": "BXH-10",
      "bladeZh": "空力天马",
      "ratchet": "1-60",
      "bit": "K",
      "score": 150,
      "wins": 76,
      "first": 16,
      "second": 2,
      "third": 58,
      "champRate": 0.2105,
      "recent90": 0,
      "lastDate": "2026-09-01"
    },
    {
      "rank": 27,
      "bladeCode": "BX-23",
      "bladeZh": "凤凰飞翼",
      "ratchet": "9-60",
      "bit": "R",
      "score": 148,
      "wins": 77,
      "first": 14,
      "second": 7,
      "third": 56,
      "champRate": 0.1818,
      "recent90": 0,
      "lastDate": "2026-09-01"
    },
    {
      "rank": 28,
      "bladeCode": "BX-23",
      "bladeZh": "凤凰飞翼",
      "ratchet": "7-60",
      "bit": "R",
      "score": 140,
      "wins": 59,
      "first": 18,
      "second": 3,
      "third": 38,
      "champRate": 0.3051,
      "recent90": 1,
      "lastDate": "2026-12-02"
    },
    {
      "rank": 29,
      "bladeCode": "UX-03",
      "bladeZh": "魔导神杖",
      "ratchet": "1-60",
      "bit": "R",
      "score": 139,
      "wins": 60,
      "first": 16,
      "second": 9,
      "third": 35,
      "champRate": 0.2667,
      "recent90": 0,
      "lastDate": "2026-09-01"
    },
    {
      "rank": 30,
      "bladeCode": "BX-23",
      "bladeZh": "凤凰飞翼",
      "ratchet": "5-60",
      "bit": "P",
      "score": 130,
      "wins": 65,
      "first": 14,
      "second": 5,
      "third": 46,
      "champRate": 0.2154,
      "recent90": 0,
      "lastDate": "2025-12-28"
    },
    {
      "rank": 31,
      "bladeCode": "UX-15-01",
      "bladeZh": "鲛鲨狂鳞",
      "ratchet": "1-60",
      "bit": "R",
      "score": 130,
      "wins": 49,
      "first": 13,
      "second": 15,
      "third": 21,
      "champRate": 0.2653,
      "recent90": 2,
      "lastDate": "2026-12-02"
    },
    {
      "rank": 32,
      "bladeCode": "UX-08",
      "bladeZh": "霜辉银狼",
      "ratchet": "9-60",
      "bit": "B",
      "score": 130,
      "wins": 72,
      "first": 12,
      "second": 4,
      "third": 56,
      "champRate": 0.1667,
      "recent90": 0,
      "lastDate": "2026-03-02"
    },
    {
      "rank": 33,
      "bladeCode": "BXH-10",
      "bladeZh": "空力天马",
      "ratchet": "1-60",
      "bit": "L",
      "score": 129,
      "wins": 62,
      "first": 13,
      "second": 9,
      "third": 40,
      "champRate": 0.2097,
      "recent90": 0,
      "lastDate": "2026-05-03"
    },
    {
      "rank": 34,
      "bladeCode": "UX-03",
      "bladeZh": "魔导神杖",
      "ratchet": "3-60",
      "bit": "H",
      "score": 128,
      "wins": 65,
      "first": 12,
      "second": 7,
      "third": 46,
      "champRate": 0.1846,
      "recent90": 0,
      "lastDate": "2026-09-01"
    },
    {
      "rank": 35,
      "bladeCode": "BX-24-01",
      "bladeZh": "飞龙旋翼(绿)",
      "ratchet": "1-60",
      "bit": "K",
      "score": 126,
      "wins": 62,
      "first": 13,
      "second": 4,
      "third": 45,
      "champRate": 0.2097,
      "recent90": 0,
      "lastDate": "2026-05-17"
    },
    {
      "rank": 36,
      "bladeCode": "UX-01",
      "bladeZh": "苍龙爆刃",
      "ratchet": "1-60",
      "bit": "LF",
      "score": 126,
      "wins": 55,
      "first": 16,
      "second": 4,
      "third": 35,
      "champRate": 0.2909,
      "recent90": 0,
      "lastDate": "2025-11-02"
    },
    {
      "rank": 37,
      "bladeCode": "BX-34",
      "bladeZh": "苍穹龙骑士(左)",
      "ratchet": "3-60",
      "bit": "E",
      "score": 117,
      "wins": 51,
      "first": 14,
      "second": 6,
      "third": 31,
      "champRate": 0.2745,
      "recent90": 0,
      "lastDate": "2025-11-23"
    },
    {
      "rank": 38,
      "bladeCode": "UX-08",
      "bladeZh": "霜辉银狼",
      "ratchet": "9-70",
      "bit": "FB",
      "score": 116,
      "wins": 62,
      "first": 10,
      "second": 6,
      "third": 46,
      "champRate": 0.1613,
      "recent90": 0,
      "lastDate": "2026-09-01"
    },
    {
      "rank": 39,
      "bladeCode": "BX-24-01",
      "bladeZh": "飞龙旋翼(绿)",
      "ratchet": "9-60",
      "bit": "R",
      "score": 116,
      "wins": 52,
      "first": 13,
      "second": 4,
      "third": 35,
      "champRate": 0.25,
      "recent90": 0,
      "lastDate": "2026-03-08"
    },
    {
      "rank": 40,
      "bladeCode": "BX-23",
      "bladeZh": "凤凰飞翼",
      "ratchet": "1-60",
      "bit": "P",
      "score": 115,
      "wins": 62,
      "first": 11,
      "second": 3,
      "third": 48,
      "champRate": 0.1774,
      "recent90": 0,
      "lastDate": "2025-12-28"
    },
    {
      "rank": 41,
      "bladeCode": "BXH-10",
      "bladeZh": "空力天马",
      "ratchet": "1-60",
      "bit": "LR",
      "score": 115,
      "wins": 67,
      "first": 9,
      "second": 3,
      "third": 55,
      "champRate": 0.1343,
      "recent90": 0,
      "lastDate": "2026-09-01"
    },
    {
      "rank": 42,
      "bladeCode": "UX-15-01",
      "bladeZh": "鲛鲨狂鳞",
      "ratchet": "9-60",
      "bit": "LR",
      "score": 113,
      "wins": 45,
      "first": 14,
      "second": 5,
      "third": 26,
      "champRate": 0.3111,
      "recent90": 0,
      "lastDate": "2026-05-01"
    },
    {
      "rank": 43,
      "bladeCode": "UX-10-01",
      "bladeZh": "骑士圆甲",
      "ratchet": "1-60",
      "bit": "R",
      "score": 112,
      "wins": 71,
      "first": 4,
      "second": 14,
      "third": 53,
      "champRate": 0.0563,
      "recent90": 0,
      "lastDate": "2026-03-07"
    },
    {
      "rank": 44,
      "bladeCode": "BX-24-01",
      "bladeZh": "飞龙旋翼(绿)",
      "ratchet": "9-60",
      "bit": "LR",
      "score": 112,
      "wins": 41,
      "first": 16,
      "second": 2,
      "third": 23,
      "champRate": 0.3902,
      "recent90": 0,
      "lastDate": "2026-09-01"
    },
    {
      "rank": 45,
      "bladeCode": "UX-03",
      "bladeZh": "魔导神杖",
      "ratchet": "1-60",
      "bit": "FB",
      "score": 111,
      "wins": 50,
      "first": 11,
      "second": 5,
      "third": 34,
      "champRate": 0.22,
      "recent90": 2,
      "lastDate": "2026-11-01"
    },
    {
      "rank": 46,
      "bladeCode": "UX-03",
      "bladeZh": "魔导神杖",
      "ratchet": "3-60",
      "bit": "FB",
      "score": 108,
      "wins": 52,
      "first": 10,
      "second": 9,
      "third": 33,
      "champRate": 0.1923,
      "recent90": 0,
      "lastDate": "2026-09-01"
    },
    {
      "rank": 47,
      "bladeCode": "UX-03",
      "bladeZh": "魔导神杖",
      "ratchet": "6-60",
      "bit": "H",
      "score": 107,
      "wins": 46,
      "first": 11,
      "second": 8,
      "third": 27,
      "champRate": 0.2391,
      "recent90": 0,
      "lastDate": "2026-04-05"
    },
    {
      "rank": 48,
      "bladeCode": "BX-34",
      "bladeZh": "苍穹龙骑士(左)",
      "ratchet": "7-60",
      "bit": "L",
      "score": 107,
      "wins": 59,
      "first": 9,
      "second": 4,
      "third": 46,
      "champRate": 0.1525,
      "recent90": 0,
      "lastDate": "2026-09-01"
    },
    {
      "rank": 49,
      "bladeCode": "UX-03",
      "bladeZh": "魔导神杖",
      "ratchet": "7-60",
      "bit": "H",
      "score": 102,
      "wins": 55,
      "first": 9,
      "second": 4,
      "third": 42,
      "champRate": 0.1636,
      "recent90": 0,
      "lastDate": "2026-03-07"
    },
    {
      "rank": 50,
      "bladeCode": "UX-17",
      "bladeZh": "陨星龙骑士(左)",
      "ratchet": "3-70",
      "bit": "J",
      "score": 101,
      "wins": 63,
      "first": 7,
      "second": 0,
      "third": 56,
      "champRate": 0.1111,
      "recent90": 0,
      "lastDate": "2026-05-22"
    },
    {
      "rank": 51,
      "bladeCode": "UX-08",
      "bladeZh": "霜辉银狼",
      "ratchet": "3-60",
      "bit": "FB",
      "score": 100,
      "wins": 45,
      "first": 12,
      "second": 3,
      "third": 30,
      "champRate": 0.2667,
      "recent90": 0,
      "lastDate": "2025-12-06"
    },
    {
      "rank": 52,
      "bladeCode": "BX-24-01",
      "bladeZh": "飞龙旋翼(绿)",
      "ratchet": "1-60",
      "bit": "LR",
      "score": 100,
      "wins": 47,
      "first": 11,
      "second": 2,
      "third": 34,
      "champRate": 0.234,
      "recent90": 0,
      "lastDate": "2026-09-01"
    },
    {
      "rank": 53,
      "bladeCode": "BXH-10",
      "bladeZh": "空力天马",
      "ratchet": "3-60",
      "bit": "R",
      "score": 100,
      "wins": 38,
      "first": 14,
      "second": 3,
      "third": 21,
      "champRate": 0.3684,
      "recent90": 0,
      "lastDate": "2025-12-28"
    },
    {
      "rank": 54,
      "bladeCode": "UX-03",
      "bladeZh": "魔导神杖",
      "ratchet": "1-60",
      "bit": "B",
      "score": 97,
      "wins": 45,
      "first": 11,
      "second": 2,
      "third": 32,
      "champRate": 0.2444,
      "recent90": 0,
      "lastDate": "2026-01-03"
    },
    {
      "rank": 55,
      "bladeCode": "BX-31-02",
      "bladeZh": "暴龙霸击",
      "ratchet": "3-60",
      "bit": "R",
      "score": 95,
      "wins": 45,
      "first": 10,
      "second": 5,
      "third": 30,
      "champRate": 0.2222,
      "recent90": 0,
      "lastDate": "2025-10-18"
    },
    {
      "rank": 56,
      "bladeCode": "UX-03",
      "bladeZh": "魔导神杖",
      "ratchet": "3-60",
      "bit": "L",
      "score": 93,
      "wins": 52,
      "first": 7,
      "second": 6,
      "third": 39,
      "champRate": 0.1346,
      "recent90": 0,
      "lastDate": "2026-02-28"
    },
    {
      "rank": 57,
      "bladeCode": "BX-31-02",
      "bladeZh": "暴龙霸击",
      "ratchet": "5-60",
      "bit": "P",
      "score": 93,
      "wins": 44,
      "first": 10,
      "second": 4,
      "third": 30,
      "champRate": 0.2273,
      "recent90": 0,
      "lastDate": "2025-11-23"
    },
    {
      "rank": 58,
      "bladeCode": "UX-01",
      "bladeZh": "苍龙爆刃",
      "ratchet": "1-60",
      "bit": "R",
      "score": 92,
      "wins": 47,
      "first": 9,
      "second": 3,
      "third": 35,
      "champRate": 0.1915,
      "recent90": 0,
      "lastDate": "2025-12-06"
    },
    {
      "rank": 59,
      "bladeCode": "UX-15-01",
      "bladeZh": "鲛鲨狂鳞",
      "ratchet": "7-60",
      "bit": "LR",
      "score": 88,
      "wins": 33,
      "first": 12,
      "second": 1,
      "third": 20,
      "champRate": 0.3636,
      "recent90": 0,
      "lastDate": "2026-09-01"
    },
    {
      "rank": 60,
      "bladeCode": "BXH-10",
      "bladeZh": "空力天马",
      "ratchet": "7-60",
      "bit": "R",
      "score": 87,
      "wins": 39,
      "first": 10,
      "second": 3,
      "third": 26,
      "champRate": 0.2564,
      "recent90": 0,
      "lastDate": "2026-01-03"
    },
    {
      "rank": 61,
      "bladeCode": "BX-23",
      "bladeZh": "凤凰飞翼",
      "ratchet": "9-60",
      "bit": "LR",
      "score": 85,
      "wins": 40,
      "first": 9,
      "second": 4,
      "third": 27,
      "champRate": 0.225,
      "recent90": 0,
      "lastDate": "2025-12-06"
    },
    {
      "rank": 62,
      "bladeCode": "UX-03",
      "bladeZh": "魔导神杖",
      "ratchet": "1-60",
      "bit": "L",
      "score": 84,
      "wins": 41,
      "first": 9,
      "second": 2,
      "third": 30,
      "champRate": 0.2195,
      "recent90": 0,
      "lastDate": "2025-12-06"
    },
    {
      "rank": 63,
      "bladeCode": "BXH-10",
      "bladeZh": "空力天马",
      "ratchet": "7-60",
      "bit": "L",
      "score": 84,
      "wins": 40,
      "first": 9,
      "second": 3,
      "third": 28,
      "champRate": 0.225,
      "recent90": 0,
      "lastDate": "2025-11-23"
    },
    {
      "rank": 64,
      "bladeCode": "UX-03",
      "bladeZh": "魔导神杖",
      "ratchet": "5-60",
      "bit": "B",
      "score": 79,
      "wins": 41,
      "first": 7,
      "second": 4,
      "third": 30,
      "champRate": 0.1707,
      "recent90": 0,
      "lastDate": "2025-11-30"
    },
    {
      "rank": 65,
      "bladeCode": "BX-31-02",
      "bladeZh": "暴龙霸击",
      "ratchet": "9-60",
      "bit": "R",
      "score": 77,
      "wins": 34,
      "first": 9,
      "second": 2,
      "third": 23,
      "champRate": 0.2647,
      "recent90": 0,
      "lastDate": "2026-05-17"
    },
    {
      "rank": 66,
      "bladeCode": "UX-16",
      "bladeZh": "时钟幻象",
      "ratchet": "4-55",
      "bit": "LO",
      "score": 76,
      "wins": 31,
      "first": 9,
      "second": 3,
      "third": 19,
      "champRate": 0.2903,
      "recent90": 0,
      "lastDate": "2026-01-28"
    },
    {
      "rank": 67,
      "bladeCode": "UX-15-01",
      "bladeZh": "鲛鲨狂鳞",
      "ratchet": "9-60",
      "bit": "FB",
      "score": 75,
      "wins": 25,
      "first": 10,
      "second": 3,
      "third": 12,
      "champRate": 0.4,
      "recent90": 1,
      "lastDate": "2026-12-02"
    },
    {
      "rank": 68,
      "bladeCode": "UX-16",
      "bladeZh": "时钟幻象",
      "ratchet": "4-55",
      "bit": "UN",
      "score": 75,
      "wins": 28,
      "first": 9,
      "second": 3,
      "third": 16,
      "champRate": 0.3214,
      "recent90": 1,
      "lastDate": "2026-11-01"
    },
    {
      "rank": 69,
      "bladeCode": "BX-34",
      "bladeZh": "苍穹龙骑士(左)",
      "ratchet": "5-60",
      "bit": "L",
      "score": 74,
      "wins": 40,
      "first": 5,
      "second": 7,
      "third": 28,
      "champRate": 0.125,
      "recent90": 0,
      "lastDate": "2026-03-07"
    },
    {
      "rank": 70,
      "bladeCode": "BXH-10",
      "bladeZh": "空力天马",
      "ratchet": "3-60",
      "bit": "LR",
      "score": 74,
      "wins": 38,
      "first": 7,
      "second": 2,
      "third": 29,
      "champRate": 0.1842,
      "recent90": 0,
      "lastDate": "2026-02-22"
    },
    {
      "rank": 71,
      "bladeCode": "BXH-10",
      "bladeZh": "空力天马",
      "ratchet": "3-60",
      "bit": "L",
      "score": 73,
      "wins": 37,
      "first": 6,
      "second": 5,
      "third": 26,
      "champRate": 0.1622,
      "recent90": 0,
      "lastDate": "2026-09-01"
    },
    {
      "rank": 72,
      "bladeCode": "BX-31-02",
      "bladeZh": "暴龙霸击",
      "ratchet": "1-60",
      "bit": "LR",
      "score": 72,
      "wins": 38,
      "first": 6,
      "second": 4,
      "third": 28,
      "champRate": 0.1579,
      "recent90": 0,
      "lastDate": "2025-11-30"
    },
    {
      "rank": 73,
      "bladeCode": "BX-23",
      "bladeZh": "凤凰飞翼",
      "ratchet": "7-60",
      "bit": "LR",
      "score": 72,
      "wins": 37,
      "first": 7,
      "second": 1,
      "third": 29,
      "champRate": 0.1892,
      "recent90": 0,
      "lastDate": "2025-12-28"
    },
    {
      "rank": 74,
      "bladeCode": "UX-03",
      "bladeZh": "魔导神杖",
      "ratchet": "5-60",
      "bit": "H",
      "score": 71,
      "wins": 32,
      "first": 8,
      "second": 2,
      "third": 22,
      "champRate": 0.25,
      "recent90": 0,
      "lastDate": "2025-12-28"
    },
    {
      "rank": 75,
      "bladeCode": "UX-08",
      "bladeZh": "霜辉银狼",
      "ratchet": "7-60",
      "bit": "H",
      "score": 71,
      "wins": 32,
      "first": 8,
      "second": 2,
      "third": 22,
      "champRate": 0.25,
      "recent90": 0,
      "lastDate": "2026-01-03"
    },
    {
      "rank": 76,
      "bladeCode": "BX-34",
      "bladeZh": "苍穹龙骑士(左)",
      "ratchet": "7-60",
      "bit": "E",
      "score": 71,
      "wins": 35,
      "first": 7,
      "second": 2,
      "third": 26,
      "champRate": 0.2,
      "recent90": 0,
      "lastDate": "2026-05-26"
    },
    {
      "rank": 77,
      "bladeCode": "UX-10-01",
      "bladeZh": "骑士圆甲",
      "ratchet": "3-60",
      "bit": "R",
      "score": 69,
      "wins": 31,
      "first": 7,
      "second": 4,
      "third": 20,
      "champRate": 0.2258,
      "recent90": 0,
      "lastDate": "2026-02-20"
    },
    {
      "rank": 78,
      "bladeCode": "BX-02",
      "bladeZh": "恶魔红镰",
      "ratchet": "9-60",
      "bit": "B",
      "score": 68,
      "wins": 32,
      "first": 6,
      "second": 7,
      "third": 19,
      "champRate": 0.1875,
      "recent90": 0,
      "lastDate": "2025-11-02"
    },
    {
      "rank": 79,
      "bladeCode": "BXH-10",
      "bladeZh": "空力天马",
      "ratchet": "7-60",
      "bit": "LR",
      "score": 67,
      "wins": 29,
      "first": 8,
      "second": 2,
      "third": 19,
      "champRate": 0.2759,
      "recent90": 0,
      "lastDate": "2026-01-03"
    },
    {
      "rank": 80,
      "bladeCode": "UX-08",
      "bladeZh": "霜辉银狼",
      "ratchet": "9-60",
      "bit": "LO",
      "score": 67,
      "wins": 32,
      "first": 7,
      "second": 0,
      "third": 25,
      "champRate": 0.2188,
      "recent90": 0,
      "lastDate": "2025-12-28"
    },
    {
      "rank": 81,
      "bladeCode": "BX-24-01",
      "bladeZh": "飞龙旋翼(绿)",
      "ratchet": "1-60",
      "bit": "R",
      "score": 65,
      "wins": 32,
      "first": 6,
      "second": 2,
      "third": 24,
      "champRate": 0.1875,
      "recent90": 0,
      "lastDate": "2026-05-03"
    },
    {
      "rank": 82,
      "bladeCode": "UX-08",
      "bladeZh": "霜辉银狼",
      "ratchet": "9-80",
      "bit": "FB",
      "score": 65,
      "wins": 24,
      "first": 9,
      "second": 2,
      "third": 13,
      "champRate": 0.375,
      "recent90": 0,
      "lastDate": "2025-08-23"
    },
    {
      "rank": 83,
      "bladeCode": "UX-10-01",
      "bladeZh": "骑士圆甲",
      "ratchet": "1-60",
      "bit": "LR",
      "score": 65,
      "wins": 31,
      "first": 7,
      "second": 1,
      "third": 23,
      "champRate": 0.2258,
      "recent90": 0,
      "lastDate": "2025-11-02"
    },
    {
      "rank": 84,
      "bladeCode": "UX-15-01",
      "bladeZh": "鲛鲨狂鳞",
      "ratchet": "3-60",
      "bit": "R",
      "score": 64,
      "wins": 23,
      "first": 8,
      "second": 2,
      "third": 13,
      "champRate": 0.3478,
      "recent90": 0,
      "lastDate": "2026-09-01"
    },
    {
      "rank": 85,
      "bladeCode": "UX-08",
      "bladeZh": "霜辉银狼",
      "ratchet": "3-60",
      "bit": "H",
      "score": 64,
      "wins": 31,
      "first": 6,
      "second": 3,
      "third": 22,
      "champRate": 0.1935,
      "recent90": 0,
      "lastDate": "2026-03-22"
    },
    {
      "rank": 86,
      "bladeCode": "UX-13",
      "bladeZh": "魔像奇岩",
      "ratchet": "9-60",
      "bit": "FB",
      "score": 63,
      "wins": 34,
      "first": 3,
      "second": 5,
      "third": 26,
      "champRate": 0.0882,
      "recent90": 1,
      "lastDate": "2026-11-01"
    },
    {
      "rank": 87,
      "bladeCode": "UX-01",
      "bladeZh": "苍龙爆刃",
      "ratchet": "1-60",
      "bit": "LR",
      "score": 63,
      "wins": 35,
      "first": 4,
      "second": 4,
      "third": 27,
      "champRate": 0.1143,
      "recent90": 0,
      "lastDate": "2026-05-01"
    },
    {
      "rank": 88,
      "bladeCode": "UX-15-01",
      "bladeZh": "鲛鲨狂鳞",
      "ratchet": "7-60",
      "bit": "K",
      "score": 62,
      "wins": 24,
      "first": 8,
      "second": 1,
      "third": 15,
      "champRate": 0.3333,
      "recent90": 0,
      "lastDate": "2025-12-06"
    },
    {
      "rank": 89,
      "bladeCode": "BX-34",
      "bladeZh": "苍穹龙骑士(左)",
      "ratchet": "4-55",
      "bit": "E",
      "score": 61,
      "wins": 27,
      "first": 5,
      "second": 8,
      "third": 14,
      "champRate": 0.1852,
      "recent90": 0,
      "lastDate": "2025-10-18"
    },
    {
      "rank": 90,
      "bladeCode": "BX-24-01",
      "bladeZh": "飞龙旋翼(绿)",
      "ratchet": "7-60",
      "bit": "K",
      "score": 60,
      "wins": 26,
      "first": 7,
      "second": 1,
      "third": 18,
      "champRate": 0.2692,
      "recent90": 0,
      "lastDate": "2025-12-28"
    },
    {
      "rank": 91,
      "bladeCode": "UX-13",
      "bladeZh": "魔像奇岩",
      "ratchet": "1-60",
      "bit": "H",
      "score": 60,
      "wins": 20,
      "first": 8,
      "second": 4,
      "third": 8,
      "champRate": 0.4,
      "recent90": 0,
      "lastDate": "2026-09-01"
    },
    {
      "rank": 92,
      "bladeCode": "UX-08",
      "bladeZh": "霜辉银狼",
      "ratchet": "5-60",
      "bit": "H",
      "score": 60,
      "wins": 24,
      "first": 6,
      "second": 7,
      "third": 11,
      "champRate": 0.25,
      "recent90": 0,
      "lastDate": "2025-12-28"
    },
    {
      "rank": 93,
      "bladeCode": "UX-03",
      "bladeZh": "魔导神杖",
      "ratchet": "1-60",
      "bit": "LR",
      "score": 60,
      "wins": 36,
      "first": 3,
      "second": 4,
      "third": 29,
      "champRate": 0.0833,
      "recent90": 0,
      "lastDate": "2025-12-28"
    },
    {
      "rank": 94,
      "bladeCode": "UX-08",
      "bladeZh": "霜辉银狼",
      "ratchet": "5-60",
      "bit": "FB",
      "score": 60,
      "wins": 29,
      "first": 6,
      "second": 1,
      "third": 22,
      "champRate": 0.2069,
      "recent90": 0,
      "lastDate": "2026-02-03"
    },
    {
      "rank": 95,
      "bladeCode": "BX-31-02",
      "bladeZh": "暴龙霸击",
      "ratchet": "1-70",
      "bit": "K",
      "score": 60,
      "wins": 21,
      "first": 8,
      "second": 2,
      "third": 11,
      "champRate": 0.381,
      "recent90": 0,
      "lastDate": "2025-12-28"
    },
    {
      "rank": 96,
      "bladeCode": "UX-15-01",
      "bladeZh": "鲛鲨狂鳞",
      "ratchet": "4-50",
      "bit": "L",
      "score": 59,
      "wins": 31,
      "first": 4,
      "second": 4,
      "third": 23,
      "champRate": 0.129,
      "recent90": 0,
      "lastDate": "2026-02-07"
    },
    {
      "rank": 97,
      "bladeCode": "BX-23",
      "bladeZh": "凤凰飞翼",
      "ratchet": "5-60",
      "bit": "R",
      "score": 59,
      "wins": 25,
      "first": 7,
      "second": 2,
      "third": 16,
      "champRate": 0.28,
      "recent90": 0,
      "lastDate": "2025-11-23"
    },
    {
      "rank": 98,
      "bladeCode": "UX-15-01",
      "bladeZh": "鲛鲨狂鳞",
      "ratchet": "3-60",
      "bit": "L",
      "score": 59,
      "wins": 21,
      "first": 8,
      "second": 1,
      "third": 12,
      "champRate": 0.381,
      "recent90": 0,
      "lastDate": "2026-09-01"
    },
    {
      "rank": 99,
      "bladeCode": "UX-15-01",
      "bladeZh": "鲛鲨狂鳞",
      "ratchet": "1-60",
      "bit": "L",
      "score": 59,
      "wins": 22,
      "first": 6,
      "second": 3,
      "third": 13,
      "champRate": 0.2727,
      "recent90": 2,
      "lastDate": "2026-12-02"
    },
    {
      "rank": 100,
      "bladeCode": "BX-31-02",
      "bladeZh": "暴龙霸击",
      "ratchet": "7-60",
      "bit": "R",
      "score": 59,
      "wins": 31,
      "first": 4,
      "second": 5,
      "third": 22,
      "champRate": 0.129,
      "recent90": 0,
      "lastDate": "2025-12-06"
    }
  ]
}